{
  "name": {
    "en": "IcalCalendar"
  },
  "class": "other",
  "capabilities": [
    "meter_calendars_count_ical",
    "meter_total_event_count_ical"
  ],
  "platforms": [
    "local"
  ],
  "connectivity": [],
  "icon": "{{driverAssetsPath}}/icon.svg",
  "images": {
    "small": "{{driverAssetsPath}}/images/small.png",
    "large": "{{driverAssetsPath}}/images/large.png"
  },
  "pair": [
    {
      "id": "list_devices",
      "template": "list_devices",
      "navigation": {
        "next": "add_devices"
      }
    },
    {
      "id": "add_devices",
      "template": "add_devices"
    }
  ]
}
